<?xml version="1.0" encoding="utf-8"?>
<fetchdatas>
    <page>
        <datas>
            <data name="csyj" type="String">$CSYJ</data>
            <data name="csr" type="Image">$CSR</data>
            <data name="csrq" type="String">$CSRQ</data>
            <data name="fsyj" type="String">$FSYJ</data>
            <data name="fsr" type="Image">$CSR</data>
            <data name="fsrq" type="String">$CSRQ</data>
            <data name="shyj" type="String">$SHYJ</data>
            <data name="shr" type="String">$SHR</data>
            <data name="shrq" type="String">$SHRQ</data>
            <data name="xmbz" type="String">$XMBZ</data>
            <data name="slbh" type="String">$SLBH</data>
            <data name="bdcqzh" type="String">$BDCQZH</data>
            <data name="qzysxlh" type="String">$QZYSXLH</data>
            <data name="qllx" type="String">$QLLX</data>
            <data name="djlx" type="String">$DJLX</data>
            <data name="gyfs" type="String">$GYFS</data>
            <data name="sqfbcz" type="String">$SQFBCZ</data>
            <data name="qlrmc" type="String">$QLRMC</data>
            <data name="qlrzjzl" type="String">$QLRZJZL</data>
            <data name="qlrzjh" type="String">$QLRZJH</data>
            <data name="qlrdwxz" type="String">$QLRDWXZ</data>
            <data name="qlrfddbr" type="String">$QLRFDDBR</data>
            <data name="qlrfddbrdh" type="String">$QLRFDDBRDH</data>
            <data name="qlrdlr" type="String">$QLRDLR</data>
            <data name="qlrdlrdh" type="String">$QLRDLRDH</data>
            <data name="qlrdljgmc" type="String">$QLRDLJGMC</data>

            <data name="ywrmc" type="String">$YWRMC</data>
            <data name="ywrzjzl" type="String">$YWRZJZL</data>
            <data name="ywrzjh" type="String">$YWRZJH</data>
            <data name="ywrdwxz" type="String">$YWRDWXZ</data>
            <data name="ywrfddbr" type="String">$YWRFDDBR</data>
            <data name="ywrfddbrdh" type="String">$YWRFDDBRDH</data>
            <data name="ywrdlr" type="String">$YWRDLR</data>
            <data name="ywrdlrdh" type="String">$YWRDLRDH</data>
            <data name="ywrdljgmc" type="String">$YWRDLJGMC</data>

            <data name="zl" type="String">$ZL</data>
            <data name="bdcdyh" type="String">$BDCDYH</data>
            <data name="zdzhmj" type="String">$ZDZHMJ</data>
            <data name="zdzhyt" type="String">$ZDZHYT</data>
            <data name="tdqlmj" type="String">$TDQLMJ</data>
            <data name="dytdmj" type="String">$DYTDMJ</data>
            <data name="fttdmj" type="String">$FTTDMJ</data>
            <data name="jzmj" type="String">$JZMJ</data>
            <data name="fwyt" type="String">$FWYT</data>
            <data name="zcs" type="String">$ZCS</data>
            <data name="szc" type="String">$SZC</data>
            <data name="zdzhqlxz" type="String">$ZDZHQLXZ</data>
            <data name="fwxz" type="String">$FWXZ</data>
            <data name="syqx" type="String">$SYQX</data>
            <data name="zzrq" type="String">$ZZRQ</data>
            <data name="yhlx" type="String">$YHLX</data>
            <data name="lz" type="String">$LZ</data>
            <data name="ybdcdyh" type="String">$YBDCDYH</data>
            <data name="ybdcqzh" type="String">$YBDCQZH</data>

            <data name="tddyfw" type="String">$TDDYFW</data>
            <data name="tddymj" type="String">$TDDYMJ</data>
            <data name="fwdyfw" type="String">$FWDYFW</data>
            <data name="fwdymj" type="String">$FWDYMJ</data>
            <data name="zgzqqdse" type="String">$ZGZQQDSE</data>
            <data name="bdcjg" type="String">$BDCJG</data>
            <data name="dysw" type="String">$DYSW</data>
            <data name="dyfs" type="String">$DYFS</data>
            <data name="zwlxqssj" type="String">$ZWLXQSSJ</data>
            <data name="zwlxjssj" type="String">$ZWLXJSSJ</data>
            <data name="txms" type="String">$TXMS</data>
            <data name="zxdymj" type="String">$ZXDYMJ</data>
            <data name="bdcqzmfj" type="String">$BDCQZMFJ</data>

            <data name="xydzl" type="String">$XYDZL</data>
            <data name="xydbdcdyh" type="String">$XYDBDCDYH</data>
            <data name="dybdcqzh" type="String">$DYBDCQZH</data>
            <data name="xydbz" type="String">$XYDBZ</data>

            <data name="bdcqzsfj" type="String">$BDCQZSFJ</data>
            <data name="qlfj" type="String">$QLFJ</data>
            <data name="qslywjbh" type="String">$QSLYWJBH</data>
            <data name="sqdjnr" type="String">$SQDJNR</data>
        </datas>
    </page>
</fetchdatas>