<?xml version="1.0" encoding="UTF-8"?>
<mappings xmlns:xsi="http://www.w3.org/2001/XMLSchema-instance" xmlns="http://dozer.sourceforge.net"
          xsi:schemaLocation="http://dozer.sourceforge.net
          http://dozer.sourceforge.net/schema/beanmapping.xsd">
    <mapping map-null="true" map-empty-string="true" type="one-way" wildcard="false">
        <class-a>cn.gtmap.realestate.common.core.domain.exchange.DjfDjSzDO</class-a>
        <class-b>com.alibaba.fastjson.JSONObject</class-b>
        <field>
            <a>ywh</a>
            <b>YWH</b>
        </field>
        <field>
            <a>ysdm</a>
            <b>YSDM</b>
        </field>
        <field>
            <a>szmc</a>
            <b>SZMC</b>
        </field>
        <field>
            <a>szzh</a>
            <b>SZZH</b>
        </field>
        <field>
            <a>bz</a>
            <b>BZ</b>
        </field>
        <field>
            <a>qxdm</a>
            <b>QXDM</b>
        </field>
        <field custom-converter="cn.gtmap.realestate.common.core.dozer.converters.gtmap.DefaultValueCustomConvert"
               custom-converter-param="空">
            <a>ysxlh</a>
            <b>YSXLH</b>
        </field>
        <field custom-converter="cn.gtmap.realestate.common.core.dozer.converters.gtmap.DefaultValueCustomConvert"
               custom-converter-param="空">
            <a>szry</a>
            <b>SZRY</b>
        </field>
        <field custom-converter="cn.gtmap.realestate.common.core.dozer.converters.gtmap.NewDateCustomConverter">
            <a>szsj</a>
            <b>SZSJ</b>
        </field>
    </mapping>

</mappings>
