<?xml version="1.0" encoding="UTF-8"?>
<mappings xmlns:xsi="http://www.w3.org/2001/XMLSchema-instance" xmlns="http://dozer.sourceforge.net"
          xsi:schemaLocation="http://dozer.sourceforge.net
          http://dozer.sourceforge.net/schema/beanmapping.xsd">
    <mapping type="one-way" wildcard="false">
        <class-a>cn.gtmap.realestate.exchange.core.dto.wwsq.dyxxAndYdyFyxx.request.DyxxAndYdaxxFyRequestDTO</class-a>
        <class-b>java.util.HashMap</class-b>
        <field>
            <a>cqzh</a>
            <b key="cqzh">this</b>
        </field>
        <field>
            <a>bdcdjzmh</a>
            <b key="bdcdjzmh">this</b>
        </field>
        <field>
            <a>cqzhjc</a>
            <b key="cqzhlsh">this</b>
        </field>
        <field>
            <a>bdcdjzmhjc</a>
            <b key="zmzhlsh">this</b>
        </field>
        <field>
            <a>dyqr</a>
            <b key="dyqr">this</b>
        </field>
        <field>
            <a>dyqrzjh</a>
            <b key="dyqrzjh">this</b>
        </field>
        <field>
            <a>djkssj</a>
            <b key="djkssj">this</b>
        </field>
        <field>
            <a>djjssj</a>
            <b key="djjssj">this</b>
        </field>
        <field>
            <a>qszt</a>
            <b key="qszt">this</b>
        </field>
        <field>
            <a>dyr</a>
            <b key="dyr">this</b>
        </field>
        <field>
            <a>dyrzjh</a>
            <b key="dyrzjh">this</b>
        </field>
        <field>
            <a>sfcf</a>
            <b key="sfcf">this</b>
        </field>
        <field>
            <a>sfydy</a>
            <b key="sfydy">this</b>
        </field>
        <field>
            <a>zl</a>
            <b key="zl">this</b>
        </field>
        <field>
            <a>dysw</a>
            <b key="dysw">this</b>
        </field>
        <field>
            <a>xzqdm</a>
            <b key="xzqdm">this</b>
        </field>
        <field>
            <a>slsj</a>
            <b key="slsj">this</b>
        </field>
        <field>
            <a>nwslbh</a>
            <b key="nwslbh">this</b>
        </field>
    </mapping>
</mappings>
