<?xml version="1.0" encoding="UTF-8"?>
<mappings xmlns:xsi="http://www.w3.org/2001/XMLSchema-instance" xmlns="http://dozer.sourceforge.net"
          xsi:schemaLocation="http://dozer.sourceforge.net
          http://dozer.sourceforge.net/schema/beanmapping.xsd">
    <mapping map-null="false" map-empty-string="false" type="one-way" wildcard="false">
        <class-a>com.alibaba.fastjson.JSONObject</class-a>
        <class-b>com.alibaba.fastjson.JSONObject</class-b>
        <field map-id="qlr">
            <a>qlrxx</a>
            <b>qlrxx</b>
            <b-deep-index-hint>com.alibaba.fastjson.JSONArray</b-deep-index-hint>
        </field>
        <field custom-converter="cn.gtmap.realestate.exchange.core.dozer.converters.ConstantsCustomConvert"
               custom-converter-param="N">
            <a>qlrxx</a>
            <b>sfghyt</b>
        </field>
        <field custom-converter="cn.gtmap.realestate.exchange.core.dozer.converters.ConstantsCustomConvert"
               custom-converter-param="1">
            <a>qlrxx</a>
            <b>zslx</b>
        </field>
        <field custom-converter="cn.gtmap.realestate.exchange.core.dozer.converters.ConstantsCustomConvert"
               custom-converter-param="1">
            <a>qlrxx</a>
            <b>sjsl</b>
        </field>
    </mapping>

    <mapping map-id="qlr" map-null="false" map-empty-string="false" wildcard="false">
        <class-a>com.alibaba.fastjson.JSONObject</class-a>
        <class-b>com.alibaba.fastjson.JSONObject</class-b>
        <field>
            <a>xm</a>
            <b>qlrmc</b>
        </field>
        <field>
            <a>zjh</a>
            <b>zjh</b>
        </field>
    </mapping>

</mappings>
